opszero_rustypy-0.1.0.dist-info/METADATA
opszero_rustypy-0.1.0.dist-info/WHEEL
opszero_rustypy-0.1.0.dist-info/license_files/LICENSE
opszero_rustypy/__init__.py
opszero_rustypy/opszero_rustypy.cpython-311-x86_64-linux-gnu.so
opszero_rustypy-0.1.0.dist-info/RECORD
